README.txt
setup.cfg
setup.py
collective/__init__.py
collective.transform.creole.egg-info/PKG-INFO
collective.transform.creole.egg-info/SOURCES.txt
collective.transform.creole.egg-info/dependency_links.txt
collective.transform.creole.egg-info/entry_points.txt
collective.transform.creole.egg-info/namespace_packages.txt
collective.transform.creole.egg-info/not-zip-safe
collective.transform.creole.egg-info/requires.txt
collective.transform.creole.egg-info/top_level.txt
collective/transform/__init__.py
collective/transform/creole/README.txt
collective/transform/creole/__init__.py
collective/transform/creole/configure.zcml
collective/transform/creole/creole_to_html.py
collective/transform/creole/setuphandlers.py
collective/transform/creole/tests.py
collective/transform/creole/version.txt
collective/transform/creole/profiles/default/collective.transform.creole-default.txt
collective/transform/creole/profiles/uninstall/collective.transform.creole-uninstall.txt
docs/HISTORY.txt
docs/INSTALL.txt
docs/LICENSE.GPL
docs/LICENSE.txt