Metadata-Version: 1.0
Name: collective.transform.creole
Version: 1.1
Summary: Creole wiki text transform for Plone
Home-page: https://svn.plone.org/svn/collective/collective.transform.creole
Author: Clayton Parker
Author-email: info AT claytron DOT com
License: GPL
Platform: UNKNOWN
Classifier: Framework :: Plone
Classifier: Programming Language :: Python
Classifier: Topic :: Software Development :: Libraries :: Python Modules
